xlsx_import_tools/__init__.py
xlsx_import_tools/admin.py
xlsx_import_tools/apps.py
xlsx_import_tools/definitions.py
xlsx_import_tools/migrations/0001_initial.py
xlsx_import_tools/migrations/0002_auto_20201130_1512.py
xlsx_import_tools/migrations/0003_auto_20201203_0829.py
xlsx_import_tools/migrations/0004_auto_20201203_1300.py
xlsx_import_tools/migrations/__init__.py
xlsx_import_tools/models.py
xlsx_import_tools/validators.py
xlsx_import_tools/workbook_validator.py
xlsx_import_tools-0.1.1.dist-info/LICENSE
xlsx_import_tools-0.1.1.dist-info/WHEEL
xlsx_import_tools-0.1.1.dist-info/METADATA
xlsx_import_tools-0.1.1.dist-info/RECORD
