Metadata-Version: 2.1
Name: xlsx-import-tools
Version: 0.1.1
Summary: 
Author: Josh Brooks
Author-email: josh@catalpa.io
Requires-Python: >=3.8,<4.0
Classifier: Programming Language :: Python :: 3
Classifier: Programming Language :: Python :: 3.10
Classifier: Programming Language :: Python :: 3.8
Classifier: Programming Language :: Python :: 3.9
Requires-Dist: openpyxl (>=3.0.9,<4.0.0)
